{
  "basics": {
    "name": "Zhaomin Wu",
    "position": "Research Fellow in National University of Singapore",
    "image": "",
    "email": "zhaomin@nus.edu.sg",
    "url": "https://www.zhaominwu.com"
  },
  "education": [
    {
      "institution": "National University of Singapore",
      "location": "Singapore",
      "url": "https://www.nus.edu.sg/",
      "area": "Computer Science",
      "studyType": "Doctor of Philosophy",
      "startDate": "2019-08-01",
      "endDate": "2024-05-03",
      "score": "GPA: 4.67/5.0"
    },
    {
      "institution": "Huazhong University of Science and Technology",
        "location": "Wuhan, China",
        "url": "https://www.hust.edu.cn/",
        "area": "Computer Science and Technology",
        "studyType": "Bachelor of Engineering",
        "startDate": "2015-09-01",
        "endDate": "2019-06-30",
        "score": "GPA: 3.91/4.0; Rank: 10/281"
    },
    {
      "institution": "No.1 Middle School affiliated to Central China Normal University",
        "location": "Wuhan, China",
        "url": "https://www.hzsdyfz.com.cn/",
        "area": "Science",
        "studyType": "High School",
        "startDate": "2012-09-01",
        "endDate": "2015-06-30"
    }
  ],
  "awards": [
    {
      "title": "Honorable Mention for Best PhD Thesis Award",
      "date": "2023",
      "awarder": "School of Computing (SoC), National University of Singapore (NUS)",
      "url": "",
      "summary": "Top 5 among PhD applicants"
    },
    {
      "title": "Dean's Graduate Research Excellence Award",
      "date": "2023",
      "awarder": "National University of Singapore (NUS)",
      "url": "",
      "summary": "For senior PhD students who have made significant research achievements during their PhD study."
    },
    {
      "title": "Outstanding undergraduate thesis",
      "date": "2019",
      "awarder": "Department of Computer Science and Technology, Huazhong University of Science and Technology (HUST)",
      "url": "",
      "summary": "Top 5% among undergraduate students."
    },
    {
      "title": "Distinguished Graduate",
      "date": "2019",
      "awarder": "Huazhong University of Science and Technology (HUST)",
      "url": "",
      "summary": "Top 40% among undergraduate students."
    },
    {
      "title": "Meritorious Winner in Mathematical Contest in Modeling (MCM/ICM)",
      "date": "2018",
      "awarder": "Consortium for Mathematics and Its Applications (COMAP)",
      "url": "",
      "summary": "Top 10% among all participants worldwide."
    },
    {
      "title": "National Scholarship",
      "date": "2017",
      "awarder": "Ministry of Education of China",
      "url": "",
      "summary": "Top 1% among undergraduate students."
    },
    {
      "title": "Outstanding Students",
      "date": "2016",
      "awarder": "Huazhong University of Science and Technology (HUST)",
      "url": "",
      "summary": "Top 1% among undergraduate students."
    },
    {
      "title": "Third Prize in National College Students Connected Smarter System Innovation Competition",
      "date": "2016",
      "awarder": "Ministry of Education of China and Chinese Institute of Electronics",
      "url": "",
      "summary": "Top 10% among all participants nationwide."
    },
    {
      "title": "Merit Student",
      "date": "2015",
      "awarder": "Huazhong University of Science and Technology (HUST)",
      "url": "",
      "summary": "Top 5% among undergraduate students."
    }
  ],
  "skills": [
    {
      "name": "Programming Languages (Familiar)",
      "keywords": [
        "Python",
        "C",
        "C++"
      ]
    },
    {
      "name": "Tools (Familiar)",
      "keywords": [
        "PyTorch",
        "Linux Command Line",
        "Latex",
        "Microsoft Office"
      ]
    },
    {
      "name": "Programming Languages (Used)",
      "keywords": [
        "Java",
        "MATLAB",
        "SQL",
        "Verilog",
        "x86 Assembly",
        "JavaScript",
        "Standard ML",
        "CUDA"
      ]
    },
    {
      "name": "Tools (Used)",
      "keywords": [
        "TensorFlow",
        "LightGBM",
        "XGBoost",
        "Qt",
        "JavaFX",
        "Win32 API",
        "Apache Cassandra",
        "MongoDB"
      ]
    }
  ],
  "languages": [
    {
      "language": "Chinese",
      "fluency": "Native speaker",
      "icon": ""
    },
    {
      "language": "English",
      "fluency": "Professional working proficiency",
      "icon": ""
    }
  ],
  "volunteer": [
    {
      "organization": "Teaching in Underprivileged Areas",
      "location": "Hunan, China",
      "position": "Teacher",
      "startDate": "2016-07",
      "endDate": "2016-08",
      "summary": "Teaching science and conducting social studies, including home visits, in underprivileged areas."
    },
    {
      "organization": "Department of Computer Science and Technology, Huazhong University of Science and Technology",
      "location": "Wuhan, China",
      "position": "President of Student Union",
      "startDate": "2017-04",
      "endDate": "2018-04",
      "summary": "Organizing department and university-level activities and events for students, and managing the department's public media channels."
    }
  ]
}
